nodejs_codegen
