Metadata-Version: 1.1
Name: nodejs-codegen
Version: 0.3.4
Summary: nodejs-codegen is a library for generating the infrastructure code of microservices in nodejs.
Home-page: https://github.com/cao5zy/nodejs-codegen
Author: Zongying Cao
Author-email: zongying.cao@dxc.com
License: Apache
Platform: UNKNOWN
Classifier: Development Status :: 4 - Beta
Classifier: Intended Audience :: Developers
Classifier: License :: OSI Approved :: Apache Software License
Classifier: Natural Language :: English
Classifier: Operating System :: OS Independent
Classifier: Programming Language :: Python :: 3
Classifier: Topic :: Software Development :: Libraries
